databases/__init__.py
databases/errors.py
databases/sqlite3.py
databases.py-1.0.13.dist-info/LICENSE
databases.py-1.0.13.dist-info/METADATA
databases.py-1.0.13.dist-info/WHEEL
databases.py-1.0.13.dist-info/top_level.txt
databases.py-1.0.13.dist-info/RECORD
