Metadata-Version: 2.1
Name: databases.py
Version: 1.0.13
Summary: Easily create and manipulate databases with databases.py
Home-page: https://github.com/kaiyoo/databases.py
Author: kaiyo
Author-email: UNKNOWN
License: UNKNOWN
Platform: UNKNOWN
Classifier: Programming Language :: Python :: 3
Classifier: License :: OSI Approved :: MIT License
Classifier: Operating System :: OS Independent
